json_merger/__init__.py
json_merger/comparator.py
json_merger/config.py
json_merger/conflict.py
json_merger/dict_merger.py
json_merger/errors.py
json_merger/graph_builder.py
json_merger/list_unify.py
json_merger/merger.py
json_merger/nothing.py
json_merger/stats.py
json_merger/utils.py
json_merger/contrib/__init__.py
json_merger/contrib/inspirehep/__init__.py
json_merger/contrib/inspirehep/author_util.py
json_merger/contrib/inspirehep/comparators.py
json_merger/contrib/inspirehep/match.py
json_merger-0.7.18.dist-info/LICENSE
json_merger-0.7.18.dist-info/METADATA
json_merger-0.7.18.dist-info/WHEEL
json_merger-0.7.18.dist-info/top_level.txt
json_merger-0.7.18.dist-info/RECORD
