Metadata-Version: 2.1
Name: json-merger
Version: 0.7.18
Summary: Python module that is able to merge json record objects.
Home-page: https://github.com/inveniosoftware-contrib/json-merger
Author: CERN
Author-email: admin@inspirehep.net
License: GPLv2
Keywords: JSON patch merge conflict
Platform: any
Classifier: Environment :: Web Environment
Classifier: Intended Audience :: Developers
Classifier: License :: OSI Approved :: GNU General Public License v2 (GPLv2)
Classifier: Operating System :: OS Independent
Classifier: Programming Language :: Python
Classifier: Topic :: Internet :: WWW/HTTP :: Dynamic Content
Classifier: Topic :: Software Development :: Libraries :: Python Modules
Classifier: Programming Language :: Python :: 2
Classifier: Programming Language :: Python :: 2.7
Classifier: Programming Language :: Python :: 3
Classifier: Programming Language :: Python :: 3.11
Classifier: Development Status :: 4 - Beta
License-File: LICENSE
Requires-Dist: inspire-dictdiffer
Requires-Dist: six>=1.10.0
Requires-Dist: pyrsistent>=0.11.13
Provides-Extra: all
Requires-Dist: editdistance>=0.3.1; extra == "all"
Requires-Dist: munkres<=1.0.12; extra == "all"
Requires-Dist: Unidecode>=0.4.19; extra == "all"
Requires-Dist: coverage>=4.0; extra == "all"
Requires-Dist: isort>=4.2.2; extra == "all"
Requires-Dist: pydocstyle>=1.0.0; extra == "all"
Requires-Dist: pytest-cache>=1.0; extra == "all"
Requires-Dist: pytest-cov>=1.8.0; extra == "all"
Requires-Dist: pytest>=4.6.11; extra == "all"
Requires-Dist: flake8>=3.9.0; extra == "all"
Provides-Extra: contrib
Requires-Dist: editdistance>=0.3.1; extra == "contrib"
Requires-Dist: munkres<=1.0.12; extra == "contrib"
Requires-Dist: Unidecode>=0.4.19; extra == "contrib"
Provides-Extra: tests
Requires-Dist: coverage>=4.0; extra == "tests"
Requires-Dist: isort>=4.2.2; extra == "tests"
Requires-Dist: pydocstyle>=1.0.0; extra == "tests"
Requires-Dist: pytest-cache>=1.0; extra == "tests"
Requires-Dist: pytest-cov>=1.8.0; extra == "tests"
Requires-Dist: pytest>=4.6.11; extra == "tests"
Requires-Dist: flake8>=3.9.0; extra == "tests"
Requires-Dist: editdistance>=0.3.1; extra == "tests"
Requires-Dist: munkres<=1.0.12; extra == "tests"
Requires-Dist: Unidecode>=0.4.19; extra == "tests"
